{
  "pools": [
    {
      "rolls": 1,
      "entries": [
        {
          "type": "minecraft:item",
          "name": "minecraft:warped_fungus_on_a_stick",
          "functions": [
            {
              "function": "set_custom_data",
              "tag": "{OneWaveOnly:1b}"
            },
            {
              "function": "minecraft:set_name",
              "entity": "this",
              "name": [
                {
                  "text": "Repelling Gauntlet",
                  "color": "gold",
                  "bold": false,
                  "italic": false
                }
              ]
            },
            {
              "function": "minecraft:set_lore",
              "entity": "this",
              "lore": [
                {
                  "text": "Right-Click:",
                  "color": "yellow",
                  "italic": false
                },
                [
                  {
                    "text": " Repels",
                    "color": "gold",
                    "italic": false
                  },
                  {
                    "text": " enemies away from you!",
                    "color": "gray",
                    "italic": false
                  }
                ]
              ],
              "mode": "replace_all"
            },
            {
              "function": "minecraft:set_components",
              "components": {
                "minecraft:hide_additional_tooltip": {},
                "minecraft:attribute_modifiers": {
                  "modifiers": [],
                  "show_in_tooltip": false
                }
              }
            }
          ]
        }
      ]
    }
  ]
}