{
  "pools": [
    {
      "rolls": 1,
      "entries": [
        {
          "type": "minecraft:item",
          "name": "minecraft:ender_eye",
          "functions": [
            {
              "function": "minecraft:set_custom_data",
              "tag": "{MenuItem:1b}"
            },
            {
              "function": "minecraft:set_name",
              "entity": "this",
              "name": [
                {
                  "text": "Gold Telekinesis",
                  "color": "light_purple",
                  "bold": false,
                  "italic": false
                }
              ]
            },
            {
              "function": "minecraft:set_lore",
              "entity": "this",
              "lore": [
                {
                  "text": "Teleports gold directly",
                  "color": "gray",
                  "italic": false
                },
                {
                  "text": "into your pouch, instead of it",
                  "color": "gray",
                  "italic": false
                },
                {
                  "text": "dropping on the ground.",
                  "color": "gray",
                  "italic": false
                },
                {
                  "text": " "
                }
              ],
              "mode": "replace_all"
            },
            {
              "function": "minecraft:set_components",
              "components": {
                "minecraft:hide_additional_tooltip": {},
                "minecraft:attribute_modifiers": {
                  "modifiers": [],
                  "show_in_tooltip": false
                }
              }
            },
            {
              "function": "minecraft:set_components",
              "components": {
                "minecraft:attribute_modifiers": {
                  "modifiers": [],
                  "show_in_tooltip": false
                },
                "minecraft:hide_additional_tooltip": {}
              }
            }
          ]
        }
      ]
    }
  ]
}